UIDep-1.1.0.10.data/purelib/UIDep/CommonServiceLocator.dll
UIDep-1.1.0.10.data/purelib/UIDep/ErrorHandler.dll
UIDep-1.1.0.10.data/purelib/UIDep/GalaSoft.MvvmLight.Extras.dll
UIDep-1.1.0.10.data/purelib/UIDep/GalaSoft.MvvmLight.Platform.dll
UIDep-1.1.0.10.data/purelib/UIDep/GalaSoft.MvvmLight.dll
UIDep-1.1.0.10.data/purelib/UIDep/Hsc.dll
UIDep-1.1.0.10.data/purelib/UIDep/Newtonsoft.Json.dll
UIDep-1.1.0.10.data/purelib/UIDep/PresentationFramework.Aero2.dll
UIDep-1.1.0.10.data/purelib/UIDep/StationNetCore.dll
UIDep-1.1.0.10.data/purelib/UIDep/System.Windows.Interactivity.dll
UIDep-1.1.0.10.data/purelib/UIDep/UIDepHelper.py
UIDep-1.1.0.10.data/purelib/UIDep/WPFMessageBox.dll
UIDep-1.1.0.10.data/purelib/UIDep/Xceed.Wpf.DataGrid.dll
UIDep-1.1.0.10.data/purelib/UIDep/Xceed.Wpf.Toolkit.dll
UIDep-1.1.0.10.data/purelib/UIDep/__init__.py
UIDep-1.1.0.10.data/purelib/UIDep/imo.ico
UIDep-1.1.0.10.data/purelib/UIDep/log4net.dll
UIDep-1.1.0.10.data/purelib/UIDep/logo.png
UIDep-1.1.0.10.data/purelib/UIDep/version.txt
UIDep-1.1.0.10.dist-info/LICENSE.txt
UIDep-1.1.0.10.dist-info/METADATA
UIDep-1.1.0.10.dist-info/WHEEL
UIDep-1.1.0.10.dist-info/top_level.txt
UIDep-1.1.0.10.dist-info/RECORD
