Metadata-Version: 2.1
Name: UIDep
Version: 1.1.0.10
Summary: UNKNOWN
Home-page: UNKNOWN
Author: elton
Author-email: elton.tian@group.com
License: UNKNOWN
Platform: UNKNOWN
Classifier: Development Status :: 5 - Production/Stable
Classifier: Intended Audience :: Developers
Classifier: Topic :: Software Development :: Libraries
Classifier: License :: Other/Proprietary License
Classifier: Programming Language :: Python
Requires-Dist: setuptools (~=46.1.3)
